autopdfparse/__init__.py
autopdfparse/config.py
autopdfparse/default_prompts.py
autopdfparse/exceptions.py
autopdfparse/models.py
autopdfparse/py.typed
autopdfparse/providers/__init__.py
autopdfparse/providers/anthropic.py
autopdfparse/providers/gemini.py
autopdfparse/providers/openai.py
autopdfparse/services/__init__.py
autopdfparse/services/parser.py
autopdfparse/services/vision.py
autopdfparse/sync/__init__.py
autopdfparse/sync/providers/__init__.py
autopdfparse/sync/providers/anthropic.py
autopdfparse/sync/providers/gemini.py
autopdfparse/sync/providers/openai.py
autopdfparse/sync/services/__init__.py
autopdfparse/sync/services/parser.py
autopdfparse/sync/services/vision.py
autopdfparse-0.1.2.dist-info/METADATA
autopdfparse-0.1.2.dist-info/WHEEL
autopdfparse-0.1.2.dist-info/licenses/LICENSE
autopdfparse-0.1.2.dist-info/RECORD
