Metadata-Version: 2.4
Name: autopdfparse
Version: 0.1.2
Summary: A Python package for parsing PDF documents using AI vision models
Project-URL: Homepage, https://github.com/ChidiRnweke/AutoPDFParse
Project-URL: Issues, https://github.com/ChidiRnweke/AutoPDFParse/issues
Author-email: Chidi Nweke <chidi125@gmail.com>
License-Expression: MIT
License-File: LICENSE
Requires-Python: >=3.12
Requires-Dist: pillow>=11.2.1
Requires-Dist: pydantic>=2.0.0
Requires-Dist: pymupdf>=1.25.5
Provides-Extra: anthropic
Requires-Dist: anthropic>=0.51.0; extra == 'anthropic'
Requires-Dist: json-repair>=0.44.1; extra == 'anthropic'
Provides-Extra: gemini
Requires-Dist: google-genai>=1.15.0; extra == 'gemini'
Provides-Extra: openai
Requires-Dist: openai>=1.79.0; extra == 'openai'
